symlinkConverter/__init__.py
symlinkConverter/converter.py
symlinkConverter-0.2.data/scripts/symlinkConverter
symlinkConverter-0.2.dist-info/METADATA
symlinkConverter-0.2.dist-info/WHEEL
symlinkConverter-0.2.dist-info/top_level.txt
symlinkConverter-0.2.dist-info/RECORD
