Metadata-Version: 2.1
Name: symlinkConverter
Version: 0.2
Summary: Converts Symlinks to Text files and vice-versa
Home-page: https://github.com/oparkins/symlinkConverter
Author: Owen T. Parkins
Author-email: oparkins@nibious.com
License: UNKNOWN
Platform: UNKNOWN
